genlogger/__init__.py
genlogger/generations.py
genlogger/genlogger.py
genlogger-0.1.1.dist-info/LICENSE
genlogger-0.1.1.dist-info/METADATA
genlogger-0.1.1.dist-info/WHEEL
genlogger-0.1.1.dist-info/top_level.txt
genlogger-0.1.1.dist-info/RECORD
