Metadata-Version: 2.1
Name: genlogger
Version: 0.1.1
Summary: A logger designed to bridge the Generational gap between programmers. It is designed to be be inclusive to all generations of programmers using the vocabulary they are most familiar with.
Home-page: https://github.com/pavanreddy-ml/genlogger
Author: Pavan Reddy
Author-email: preddy.osdev@gmail.com
License: MIT
Classifier: Programming Language :: Python :: 3
Classifier: License :: OSI Approved :: MIT License
Classifier: Operating System :: OS Independent
Requires-Python: >=3.9
License-File: LICENSE
Provides-Extra: testing
Requires-Dist: pytest; extra == "testing"
Requires-Dist: pytest-cov; extra == "testing"
